{
	"language":"Simplified Chinese",
	"langId": 2052,
	"author":"Tom Willow",
	"version":"0.1",
	"date":"2023-12-31",
	"data":[
		[1,"序号"],
		[2,"文件名"],
		[3,"大小"],
		[4,"编码"],
		[5,"换行符"],
		[6,"文本片段"],
		[7,"出错"],
		[8,"以下文件添加失败："],
		[9,"原因："],
		[10,"%d 个文件被判定为非文本文件、或者没有探测出字符集："],
		[11,"......等"],
		[12,"提示：使用“不过滤”模式再次添加，可以在列表框中点击右键手动指定原编码集。"],
		[13,"提示"],
		[14,"没有待转换的文件。"],
		[15,"输出目录无效。"],
		[16,"转换成功 %d 个文件。"],
		[17,"以下文件转换失败："],
		[18,"剩余文件由于取消操作所以未做处理。"],
		[19,"转换结果"],
		[20,"注意：GB18030等多个编码在纯英文（只有ASCII码）的情况下和UTF-8编码位重合，所以可能会出现转换后显示为UTF-8编码的情况。"],
		[21,"支持以下格式："],
		[22,"(分隔符允许空格、逗号、竖线，后缀允许带*.或者不带)"],
		[23,"没有指定要过滤的后缀。"],
		[24,"指定的后缀过滤器无效："],
		[25,"所有文件"],
		[26,"以下文件设置字符集失败："],
		[27,"内存不足。"],
		[28,"取消"],
		[29,"开始转换"],
		[30,"内容包含无效字符"],
		[31,"转换到目标编码会丢失字符："],
		[32,"暂不支持：%s，请联系作者。"],
		[33,"重复添加"],
		[34,"未探测出编码集"],
		[35,"写入失败："],
		[36,"文件大小超出限制"],
		[37,"打开文件失败："],
		[38,"文件列表"],
		[39,"1. 设置文件过滤："],
		[40,"不过滤"],
		[41,"智能识别文本文件"],
		[42,"只要指定后缀的文件："],
		[43,"2. 添加要转换的文件或文件夹："],
		[44,"添加文件"],
		[45,"添加文件夹"],
		[46,"3. 选择转出位置："],
		[47,"转出到原文件"],
		[48,"转出到文件夹："],
		[49,"4. 指定转出字符集："],
		[50,"其他："],
		[51,"转换换行符"],
		[52,"清空列表"],
		[53,"用记事本打开"],
		[54,"指定原编码"],
		[55,"移除"],
		[56,"选择文件夹"]
	]
}